{
    "behavior": "", 
    "checkable": false, 
    "class": "input", 
    "clickable": true, 
    "content-desc": "", 
    "enabled": true, 
    "focusable": true, 
    "focused": false, 
    "hash": "alm1M2WZx5eZenu9ja3Lcg==\n", 
    "height": 50, 
    "hier_level": 0, 
    "human_hash": "input_X461_Y363_W600_H50", 
    "human_readable": "input_461_363_600_50_input_0000ffffffffffffffff1fff0fff0fff0fff0fffffffffffffffffffffff0000_9d4568c009d203ab10e33ea9953a0264", 
    "image_path": "MGU5NTE1Y2ZmZDY3ODQwZjgxMGY5NDNiMDY0NDdjNjg.png", 
    "index": -1, 
    "internal": {
        "elem_dict": {
            "attributes": {
                "autocomplete": "address-line2", 
                "class": "kib-form-input__control", 
                "id": "shipping-street-line2-textbox", 
                "maxlength": "35"
            }, 
            "background-color": "rgb(255, 255, 255)", 
            "class": "input", 
            "color": "rgb(51, 51, 51)", 
            "cssClass": "kib-form-input__control", 
            "domLevel": 21, 
            "flags": {
                "checkable": false, 
                "clickable": true, 
                "enabled": true, 
                "focusable": true, 
                "focused": false, 
                "scrollable": false
            }, 
            "font-family": "Roboto, \"Franklin Gothic Medium\", Tahoma, sans-serif", 
            "font-weight": "400", 
            "fontSize": 16, 
            "height": 50, 
            "identifier": "shipping-street-line2-textbox", 
            "is-focused": false, 
            "is-hidden": false, 
            "name": "", 
            "tagName": "input", 
            "text": "", 
            "type": "", 
            "value": "", 
            "width": 600, 
            "x": 461, 
            "xPercent": 24.010416666666668, 
            "y": 363, 
            "yPercent": 20.790378006872853
        }, 
        "location": {
            "x": 461, 
            "y": 363
        }, 
        "size": {
            "height": 50, 
            "width": 600
        }, 
        "tag_name": "input", 
        "text": ""
    }, 
    "is_transformed": true, 
    "package": "", 
    "password": false, 
    "resource-id": "", 
    "screen_hash": "c3df65ff9e525b3fb571e76c82612363", 
    "scrollable": false, 
    "tag_name": "input", 
    "text": "", 
    "transformed": true, 
    "width": 600, 
    "x": 461, 
    "y": 363
}